arta/__init__.py
arta/_engine.py
arta/condition.py
arta/config.py
arta/exceptions.py
arta/models.py
arta/py.typed
arta/rule.py
arta/utils.py
arta-0.11.1.dist-info/licenses/LICENSE
arta-0.11.1.dist-info/licenses/NOTICE
arta-0.11.1.dist-info/METADATA
arta-0.11.1.dist-info/WHEEL
arta-0.11.1.dist-info/top_level.txt
arta-0.11.1.dist-info/RECORD
