Metadata-Version: 2.4
Name: arta
Version: 0.11.1
Summary: A Python Rules Engine - Make rule handling simple
Author: develop-cs, HugoPerrier, MathisNcl
License: Apache-2.0
Project-URL: Homepage, https://maif.github.io/arta/
Project-URL: Documentation, https://maif.github.io/arta/home/
Project-URL: Repository, https://github.com/MAIF/arta
Classifier: Development Status :: 5 - Production/Stable
Classifier: Operating System :: OS Independent
Classifier: Intended Audience :: Developers
Classifier: Intended Audience :: Information Technology
Classifier: Topic :: Software Development :: Libraries :: Python Modules
Classifier: Programming Language :: Python
Classifier: Programming Language :: Python :: 3
Classifier: Programming Language :: Python :: 3 :: Only
Classifier: Programming Language :: Python :: 3.9
Classifier: Programming Language :: Python :: 3.10
Classifier: Programming Language :: Python :: 3.11
Classifier: Programming Language :: Python :: 3.12
Classifier: Programming Language :: Python :: 3.13
Classifier: Programming Language :: Python :: 3.14
Classifier: License :: OSI Approved :: Apache Software License
Requires-Python: >=3.9
License-File: LICENSE
License-File: NOTICE
Requires-Dist: omegaconf>=2.0.0
Requires-Dist: pydantic<3.0.0
Provides-Extra: all
Requires-Dist: arta[doc,test]; extra == "all"
Provides-Extra: test
Requires-Dist: pytest; extra == "test"
Requires-Dist: pytest-cov; extra == "test"
Requires-Dist: tox; extra == "test"
Requires-Dist: tox-uv; extra == "test"
Provides-Extra: doc
Requires-Dist: mkdocs-material; extra == "doc"
Requires-Dist: mkdocstrings[python]; extra == "doc"
Requires-Dist: click<8.3.0; extra == "doc"
Dynamic: license-file
